ring_flash_attn/__init__.py
ring_flash_attn/llama3_flash_attn_varlen.py
ring_flash_attn/ring_flash_attn.py
ring_flash_attn/ring_flash_attn_varlen.py
ring_flash_attn/stripe_flash_attn.py
ring_flash_attn/triton_utils.py
ring_flash_attn/utils.py
ring_flash_attn/zigzag_ring_flash_attn.py
ring_flash_attn/zigzag_ring_flash_attn_varlen.py
ring_flash_attn/adapters/__init__.py
ring_flash_attn/adapters/hf_adapter.py
ring_flash_attn-0.1.8.dist-info/licenses/LICENSE
ring_flash_attn-0.1.8.dist-info/METADATA
ring_flash_attn-0.1.8.dist-info/WHEEL
ring_flash_attn-0.1.8.dist-info/top_level.txt
ring_flash_attn-0.1.8.dist-info/RECORD
