Metadata-Version: 2.4
Name: ring-flash-attn
Version: 0.1.8
Summary: Ring attention implementation with flash attention.
Home-page: https://github.com/zhuzilin/ring-flash-attention
Author: zhuzilin
Author-email: zhuzilin <zhuzilinallen@gmail.com>
Project-URL: Homepage, https://github.com/zhuzilin/ring-flash-attention
Project-URL: Issues, https://github.com/zhuzilin/ring-flash-attention/issues
Classifier: Programming Language :: Python :: 3
Classifier: License :: OSI Approved :: MIT License
Classifier: Operating System :: OS Independent
Requires-Python: >=3.8
License-File: LICENSE
Dynamic: author
Dynamic: home-page
Dynamic: license-file
